chat/__init__.py
chat/admin.py
chat/manager.py
chat/models.py
chat/query.py
chat/locale/pl/LC_MESSAGES/django.mo
chat/locale/pl/LC_MESSAGES/django.po
chat/migrations/0001_initial.py
chat/migrations/__init__.py
chat/south_migrations/0001_initial.py
chat/south_migrations/__init__.py
django_chat-0.1.0.dist-info/DESCRIPTION.rst
django_chat-0.1.0.dist-info/METADATA
django_chat-0.1.0.dist-info/RECORD
django_chat-0.1.0.dist-info/WHEEL
django_chat-0.1.0.dist-info/metadata.json
django_chat-0.1.0.dist-info/top_level.txt
